phlop/__init__.py
phlop/__main__.py
phlop/dict.py
phlop/logger.py
phlop/os.py
phlop/proc.py
phlop/reflection.py
phlop/string.py
phlop/sys.py
phlop/app/__init__.py
phlop/app/__main__.py
phlop/app/cmake.py
phlop/app/git.py
phlop/app/perf.py
phlop/app/sleep.py
phlop/app/stats_man.py
phlop/app/valgrind.py
phlop/app/nvidia/__init__.py
phlop/app/nvidia/__main__.py
phlop/app/nvidia/csan.py
phlop/app/nvidia/ncu.py
phlop/app/pfm/__init__.py
phlop/app/pfm/__main__.py
phlop/app/pfm/check_events.py
phlop/app/pfm/showevtinfo.py
phlop/procs/__init__.py
phlop/procs/__main__.py
phlop/procs/runtimer.py
phlop/run/__main__.py
phlop/run/mpirun_perf.py
phlop/run/mpirun_stats_man.py
phlop/run/perf.py
phlop/run/stats_man.py
phlop/run/test_cases.py
phlop/run/valgrind.py
phlop/testing/__main__.py
phlop/testing/parallel_processor.py
phlop/testing/test_cases.py
phlop/timing/__init__.py
phlop/timing/__main__.py
phlop/timing/scope_timer.py
tests/__init__.py
tests/all_concurrent.py
tests/_phlop/__init__.py
tests/_phlop/empty_test.py
tests/_phlop/run/__init__.py
tests/_phlop/run/test_test_cases.py
tests/timing/__init__.py
tests/timing/test_scope_timer.py
phlop-0.0.30.dist-info/METADATA
phlop-0.0.30.dist-info/WHEEL
phlop-0.0.30.dist-info/top_level.txt
phlop-0.0.30.dist-info/RECORD
