Metadata-Version: 2.4
Name: phlop
Version: 0.0.30
Summary: stuff and things
Project-URL: Homepage, https://github.com/PhilipDeegan/phlop/
Project-URL: Bug Tracker, https://github.com/PhilipDeegan/phlop/issues
Classifier: Programming Language :: Python :: 3
Classifier: License :: OSI Approved :: MIT License
Classifier: Operating System :: OS Independent
Requires-Python: >=3.9
